[
  {
    "audit_actions": [
      {
        "action": "publish", "time": "2019-12-14T08:16:01.779921+00:00",
        "user": {
          "avatar": "https://avatars0.githubusercontent.com/u/4852873?v=4",
          "id": 64482, "login": "akhilles", "name": "Akhil Velagapudi",
          "url": "https://github.com/akhilles"
        }
      }
    ],
    "authors": {
      "meta": {"names": ["Akhil Velagapudi <akhilvelagapudi@gmail.com>"]},
      "users": []
    },
    "crate": "crc-catalog", "crate_size": 7534,
    "created_at": "2019-12-14T08:16:01.779921+00:00",
    "dependencies": [],
    "dl_path": "/api/v1/crates/crc-catalog/0.1.0/download",
    "downloads": 97, "features": {}, "id": 196368,
    "license": "MIT OR Apache-2.0",
    "links": {
      "authors": "/api/v1/crates/crc-catalog/0.1.0/authors",
      "dependencies": "/api/v1/crates/crc-catalog/0.1.0/dependencies",
      "version_downloads": "/api/v1/crates/crc-catalog/0.1.0/downloads"
    },
    "num": "0.1.0",
    "published_by": {
      "avatar": "https://avatars0.githubusercontent.com/u/4852873?v=4",
      "id": 64482, "login": "akhilles", "name": "Akhil Velagapudi",
      "url": "https://github.com/akhilles"
    },
    "readme_path": "/api/v1/crates/crc-catalog/0.1.0/readme",
    "updated_at": "2019-12-14T08:16:01.779921+00:00", "yanked": false
  },
  {
    "audit_actions": [
      {
        "action": "publish", "time": "2020-03-17T19:08:57.784626+00:00",
        "user": {
          "avatar": "https://avatars0.githubusercontent.com/u/4852873?v=4",
          "id": 64482, "login": "akhilles", "name": "Akhil Velagapudi",
          "url": "https://github.com/akhilles"
        }
      }
    ],
    "authors": {
      "meta": {"names": ["Akhil Velagapudi <akhilvelagapudi@gmail.com>"]},
      "users": []
    },
    "crate": "crc-catalog", "crate_size": 7766,
    "created_at": "2020-03-17T19:08:57.784626+00:00",
    "dependencies": [],
    "dl_path": "/api/v1/crates/crc-catalog/1.0.0/download",
    "downloads": 132, "features": {}, "id": 222151,
    "license": "MIT OR Apache-2.0",
    "links": {
      "authors": "/api/v1/crates/crc-catalog/1.0.0/authors",
      "dependencies": "/api/v1/crates/crc-catalog/1.0.0/dependencies",
      "version_downloads": "/api/v1/crates/crc-catalog/1.0.0/downloads"
    },
    "num": "1.0.0",
    "published_by": {
      "avatar": "https://avatars0.githubusercontent.com/u/4852873?v=4",
      "id": 64482, "login": "akhilles", "name": "Akhil Velagapudi",
      "url": "https://github.com/akhilles"
    },
    "readme_path": "/api/v1/crates/crc-catalog/1.0.0/readme",
    "updated_at": "2020-03-17T19:08:57.784626+00:00", "yanked": false
  },
  {
    "audit_actions": [
      {
        "action": "publish", "time": "2020-08-08T23:07:06.154582+00:00",
        "user": {
          "avatar": "https://avatars0.githubusercontent.com/u/4852873?v=4",
          "id": 64482, "login": "akhilles", "name": "Akhil Velagapudi",
          "url": "https://github.com/akhilles"
        }
      }
    ],
    "authors": {
      "meta": {"names": ["Akhil Velagapudi <akhilvelagapudi@gmail.com>"]},
      "users": []
    },
    "crate": "crc-catalog", "crate_size": 7770,
    "created_at": "2020-08-08T23:07:06.154582+00:00",
    "dependencies": [],
    "dl_path": "/api/v1/crates/crc-catalog/1.1.0/download",
    "downloads": 1147, "features": {}, "id": 270815,
    "license": "MIT OR Apache-2.0",
    "links": {
      "authors": "/api/v1/crates/crc-catalog/1.1.0/authors",
      "dependencies": "/api/v1/crates/crc-catalog/1.1.0/dependencies",
      "version_downloads": "/api/v1/crates/crc-catalog/1.1.0/downloads"
    },
    "num": "1.1.0",
    "published_by": {
      "avatar": "https://avatars0.githubusercontent.com/u/4852873?v=4",
      "id": 64482, "login": "akhilles", "name": "Akhil Velagapudi",
      "url": "https://github.com/akhilles"
    },
    "readme_path": "/api/v1/crates/crc-catalog/1.1.0/readme",
    "updated_at": "2020-08-08T23:07:06.154582+00:00", "yanked": false
  }
]