[
  {
    "audit_actions": [],
    "authors": {
      "meta": {"names": ["David Tolnay <dtolnay@gmail.com>"]},
      "users": []
    },
    "crate": "thiserror", "crate_size": 8087,
    "created_at": "2019-10-09T18:05:40.346377+00:00",
    "dependencies": [
      {
        "crate_id": "anyhow", "default_features": true, "downloads": 0,
        "features": [], "id": 937869, "kind": "dev", "optional": false,
        "req": "^1.0", "target": null, "version_id": 181524
      },
      {
        "crate_id": "thiserror-impl", "default_features": true,
        "downloads": 0, "features": [], "id": 937868, "kind": "normal",
        "optional": false, "req": "^1.0", "target": null,
        "version_id": 181524
      }
    ],
    "dl_path": "/api/v1/crates/thiserror/1.0.0/download",
    "downloads": 372, "features": {}, "id": 181524,
    "license": "MIT OR Apache-2.0",
    "links": {
      "authors": "/api/v1/crates/thiserror/1.0.0/authors",
      "dependencies": "/api/v1/crates/thiserror/1.0.0/dependencies",
      "version_downloads": "/api/v1/crates/thiserror/1.0.0/downloads"
    },
    "num": "1.0.0",
    "published_by": {
      "avatar": "https://avatars2.githubusercontent.com/u/1940490?v=4",
      "id": 3618, "login": "dtolnay", "name": "David Tolnay",
      "url": "https://github.com/dtolnay"
    },
    "readme_path": "/api/v1/crates/thiserror/1.0.0/readme",
    "updated_at": "2019-10-09T18:05:40.346377+00:00", "yanked": false
  },
  {
    "audit_actions": [],
    "authors": {
      "meta": {"names": ["David Tolnay <dtolnay@gmail.com>"]},
      "users": []
    },
    "crate": "thiserror", "crate_size": 8228,
    "created_at": "2019-10-09T20:05:45.477119+00:00",
    "dependencies": [
      {
        "crate_id": "anyhow", "default_features": true, "downloads": 0,
        "features": [], "id": 938033, "kind": "dev", "optional": false,
        "req": "^1.0", "target": null, "version_id": 181554
      },
      {
        "crate_id": "thiserror-impl", "default_features": true,
        "downloads": 0, "features": [], "id": 938032, "kind": "normal",
        "optional": false, "req": "=1.0.0", "target": null,
        "version_id": 181554
      }
    ],
    "dl_path": "/api/v1/crates/thiserror/1.0.1/download",
    "downloads": 927, "features": {}, "id": 181554,
    "license": "MIT OR Apache-2.0",
    "links": {
      "authors": "/api/v1/crates/thiserror/1.0.1/authors",
      "dependencies": "/api/v1/crates/thiserror/1.0.1/dependencies",
      "version_downloads": "/api/v1/crates/thiserror/1.0.1/downloads"
    },
    "num": "1.0.1",
    "published_by": {
      "avatar": "https://avatars2.githubusercontent.com/u/1940490?v=4",
      "id": 3618, "login": "dtolnay", "name": "David Tolnay",
      "url": "https://github.com/dtolnay"
    },
    "readme_path": "/api/v1/crates/thiserror/1.0.1/readme",
    "updated_at": "2019-10-09T20:05:45.477119+00:00", "yanked": false
  },
  {
    "audit_actions": [],
    "authors": {
      "meta": {"names": ["David Tolnay <dtolnay@gmail.com>"]},
      "users": []
    },
    "crate": "thiserror", "crate_size": 10547,
    "created_at": "2019-10-13T01:20:13.383485+00:00",
    "dependencies": [
      {
        "crate_id": "anyhow", "default_features": true, "downloads": 0,
        "features": [], "id": 942627, "kind": "dev", "optional": false,
        "req": "^1.0", "target": null, "version_id": 182231
      },
      {
        "crate_id": "rustversion", "default_features": true, "downloads": 0,
        "features": [], "id": 942628, "kind": "dev", "optional": false,
        "req": "^1.0", "target": null, "version_id": 182231
      },
      {
        "crate_id": "thiserror-impl", "default_features": true,
        "downloads": 0, "features": [], "id": 942626, "kind": "normal",
        "optional": false, "req": "=1.0.2", "target": null,
        "version_id": 182231
      },
      {
        "crate_id": "trybuild", "default_features": true, "downloads": 0,
        "features": [], "id": 942629, "kind": "dev", "optional": false,
        "req": "^1.0", "target": null, "version_id": 182231
      }
    ],
    "dl_path": "/api/v1/crates/thiserror/1.0.2/download",
    "downloads": 5547, "features": {}, "id": 182231,
    "license": "MIT OR Apache-2.0",
    "links": {
      "authors": "/api/v1/crates/thiserror/1.0.2/authors",
      "dependencies": "/api/v1/crates/thiserror/1.0.2/dependencies",
      "version_downloads": "/api/v1/crates/thiserror/1.0.2/downloads"
    },
    "num": "1.0.2",
    "published_by": {
      "avatar": "https://avatars2.githubusercontent.com/u/1940490?v=4",
      "id": 3618, "login": "dtolnay", "name": "David Tolnay",
      "url": "https://github.com/dtolnay"
    },
    "readme_path": "/api/v1/crates/thiserror/1.0.2/readme",
    "updated_at": "2019-10-13T01:20:13.383485+00:00", "yanked": false
  },
  {
    "audit_actions": [],
    "authors": {
      "meta": {"names": ["David Tolnay <dtolnay@gmail.com>"]},
      "users": []
    },
    "crate": "thiserror", "crate_size": 10450,
    "created_at": "2019-10-19T12:57:23.414959+00:00",
    "dependencies": [
      {
        "crate_id": "anyhow", "default_features": true, "downloads": 0,
        "features": [], "id": 952503, "kind": "dev", "optional": false,
        "req": "^1.0", "target": null, "version_id": 183698
      },
      {
        "crate_id": "rustversion", "default_features": true, "downloads": 0,
        "features": [], "id": 952504, "kind": "dev", "optional": false,
        "req": "^1.0", "target": null, "version_id": 183698
      },
      {
        "crate_id": "thiserror-impl", "default_features": true,
        "downloads": 0, "features": [], "id": 952502, "kind": "normal",
        "optional": false, "req": "=1.0.3", "target": null,
        "version_id": 183698
      },
      {
        "crate_id": "trybuild", "default_features": true, "downloads": 0,
        "features": [], "id": 952505, "kind": "dev", "optional": false,
        "req": "^1.0", "target": null, "version_id": 183698
      }
    ],
    "dl_path": "/api/v1/crates/thiserror/1.0.3/download",
    "downloads": 8769, "features": {}, "id": 183698,
    "license": "MIT OR Apache-2.0",
    "links": {
      "authors": "/api/v1/crates/thiserror/1.0.3/authors",
      "dependencies": "/api/v1/crates/thiserror/1.0.3/dependencies",
      "version_downloads": "/api/v1/crates/thiserror/1.0.3/downloads"
    },
    "num": "1.0.3",
    "published_by": {
      "avatar": "https://avatars2.githubusercontent.com/u/1940490?v=4",
      "id": 3618, "login": "dtolnay", "name": "David Tolnay",
      "url": "https://github.com/dtolnay"
    },
    "readme_path": "/api/v1/crates/thiserror/1.0.3/readme",
    "updated_at": "2019-10-19T12:57:23.414959+00:00", "yanked": false
  },
  {
    "audit_actions": [],
    "authors": {
      "meta": {"names": ["David Tolnay <dtolnay@gmail.com>"]},
      "users": []
    },
    "crate": "thiserror", "crate_size": 10599,
    "created_at": "2019-10-27T15:19:48.420898+00:00",
    "dependencies": [
      {
        "crate_id": "anyhow", "default_features": true, "downloads": 0,
        "features": [], "id": 964529, "kind": "dev", "optional": false,
        "req": "^1.0", "target": null, "version_id": 185451
      },
      {
        "crate_id": "rustversion", "default_features": true, "downloads": 0,
        "features": [], "id": 964530, "kind": "dev", "optional": false,
        "req": "^1.0", "target": null, "version_id": 185451
      },
      {
        "crate_id": "thiserror-impl", "default_features": true,
        "downloads": 0, "features": [], "id": 964528, "kind": "normal",
        "optional": false, "req": "=1.0.4", "target": null,
        "version_id": 185451
      },
      {
        "crate_id": "trybuild", "default_features": true, "downloads": 0,
        "features": [], "id": 964531, "kind": "dev", "optional": false,
        "req": "^1.0", "target": null, "version_id": 185451
      }
    ],
    "dl_path": "/api/v1/crates/thiserror/1.0.4/download",
    "downloads": 18613, "features": {}, "id": 185451,
    "license": "MIT OR Apache-2.0",
    "links": {
      "authors": "/api/v1/crates/thiserror/1.0.4/authors",
      "dependencies": "/api/v1/crates/thiserror/1.0.4/dependencies",
      "version_downloads": "/api/v1/crates/thiserror/1.0.4/downloads"
    },
    "num": "1.0.4",
    "published_by": {
      "avatar": "https://avatars2.githubusercontent.com/u/1940490?v=4",
      "id": 3618, "login": "dtolnay", "name": "David Tolnay",
      "url": "https://github.com/dtolnay"
    },
    "readme_path": "/api/v1/crates/thiserror/1.0.4/readme",
    "updated_at": "2019-10-27T15:19:48.420898+00:00", "yanked": false
  },
  {
    "audit_actions": [],
    "authors": {
      "meta": {"names": ["David Tolnay <dtolnay@gmail.com>"]},
      "users": []
    },
    "crate": "thiserror", "crate_size": 11245,
    "created_at": "2019-11-10T02:41:01.690972+00:00",
    "dependencies": [
      {
        "crate_id": "anyhow", "default_features": true, "downloads": 0,
        "features": [], "id": 987353, "kind": "dev", "optional": false,
        "req": "^1.0", "target": null, "version_id": 188618
      },
      {
        "crate_id": "ref-cast", "default_features": true, "downloads": 0,
        "features": [], "id": 987354, "kind": "dev", "optional": false,
        "req": "^1.0", "target": null, "version_id": 188618
      },
      {
        "crate_id": "rustversion", "default_features": true, "downloads": 0,
        "features": [], "id": 987355, "kind": "dev", "optional": false,
        "req": "^1.0", "target": null, "version_id": 188618
      },
      {
        "crate_id": "thiserror-impl", "default_features": true,
        "downloads": 0, "features": [], "id": 987352, "kind": "normal",
        "optional": false, "req": "=1.0.5", "target": null,
        "version_id": 188618
      },
      {
        "crate_id": "trybuild", "default_features": true, "downloads": 0,
        "features": [], "id": 987356, "kind": "dev", "optional": false,
        "req": "^1.0", "target": null, "version_id": 188618
      }
    ],
    "dl_path": "/api/v1/crates/thiserror/1.0.5/download",
    "downloads": 183275, "features": {}, "id": 188618,
    "license": "MIT OR Apache-2.0",
    "links": {
      "authors": "/api/v1/crates/thiserror/1.0.5/authors",
      "dependencies": "/api/v1/crates/thiserror/1.0.5/dependencies",
      "version_downloads": "/api/v1/crates/thiserror/1.0.5/downloads"
    },
    "num": "1.0.5",
    "published_by": {
      "avatar": "https://avatars2.githubusercontent.com/u/1940490?v=4",
      "id": 3618, "login": "dtolnay", "name": "David Tolnay",
      "url": "https://github.com/dtolnay"
    },
    "readme_path": "/api/v1/crates/thiserror/1.0.5/readme",
    "updated_at": "2019-11-10T02:41:01.690972+00:00", "yanked": false
  },
  {
    "audit_actions": [],
    "authors": {
      "meta": {"names": ["David Tolnay <dtolnay@gmail.com>"]},
      "users": []
    },
    "crate": "thiserror", "crate_size": 11302,
    "created_at": "2019-11-19T07:22:29.725349+00:00",
    "dependencies": [
      {
        "crate_id": "anyhow", "default_features": true, "downloads": 0,
        "features": [], "id": 1000764, "kind": "dev", "optional": false,
        "req": "^1.0", "target": null, "version_id": 190622
      },
      {
        "crate_id": "ref-cast", "default_features": true, "downloads": 0,
        "features": [], "id": 1000765, "kind": "dev", "optional": false,
        "req": "^1.0", "target": null, "version_id": 190622
      },
      {
        "crate_id": "rustversion", "default_features": true, "downloads": 0,
        "features": [], "id": 1000766, "kind": "dev", "optional": false,
        "req": "^1.0", "target": null, "version_id": 190622
      },
      {
        "crate_id": "thiserror-impl", "default_features": true,
        "downloads": 0, "features": [], "id": 1000763, "kind": "normal",
        "optional": false, "req": "=1.0.6", "target": null,
        "version_id": 190622
      },
      {
        "crate_id": "trybuild", "default_features": true, "downloads": 0,
        "features": [], "id": 1000767, "kind": "dev", "optional": false,
        "req": "^1.0", "target": null, "version_id": 190622
      }
    ],
    "dl_path": "/api/v1/crates/thiserror/1.0.6/download",
    "downloads": 62847, "features": {}, "id": 190622,
    "license": "MIT OR Apache-2.0",
    "links": {
      "authors": "/api/v1/crates/thiserror/1.0.6/authors",
      "dependencies": "/api/v1/crates/thiserror/1.0.6/dependencies",
      "version_downloads": "/api/v1/crates/thiserror/1.0.6/downloads"
    },
    "num": "1.0.6",
    "published_by": {
      "avatar": "https://avatars2.githubusercontent.com/u/1940490?v=4",
      "id": 3618, "login": "dtolnay", "name": "David Tolnay",
      "url": "https://github.com/dtolnay"
    },
    "readme_path": "/api/v1/crates/thiserror/1.0.6/readme",
    "updated_at": "2019-11-19T07:22:29.725349+00:00", "yanked": false
  },
  {
    "audit_actions": [],
    "authors": {
      "meta": {"names": ["David Tolnay <dtolnay@gmail.com>"]},
      "users": []
    },
    "crate": "thiserror", "crate_size": 12393,
    "created_at": "2019-12-03T17:52:04.021834+00:00",
    "dependencies": [
      {
        "crate_id": "anyhow", "default_features": true, "downloads": 0,
        "features": [], "id": 1021454, "kind": "dev", "optional": false,
        "req": "^1.0", "target": null, "version_id": 193721
      },
      {
        "crate_id": "ref-cast", "default_features": true, "downloads": 0,
        "features": [], "id": 1021455, "kind": "dev", "optional": false,
        "req": "^1.0", "target": null, "version_id": 193721
      },
      {
        "crate_id": "rustversion", "default_features": true, "downloads": 0,
        "features": [], "id": 1021456, "kind": "dev", "optional": false,
        "req": "^1.0", "target": null, "version_id": 193721
      },
      {
        "crate_id": "thiserror-impl", "default_features": true,
        "downloads": 0, "features": [], "id": 1021453, "kind": "normal",
        "optional": false, "req": "=1.0.7", "target": null,
        "version_id": 193721
      },
      {
        "crate_id": "trybuild", "default_features": true, "downloads": 0,
        "features": [], "id": 1021457, "kind": "dev", "optional": false,
        "req": "^1.0", "target": null, "version_id": 193721
      }
    ],
    "dl_path": "/api/v1/crates/thiserror/1.0.7/download",
    "downloads": 136, "features": {}, "id": 193721,
    "license": "MIT OR Apache-2.0",
    "links": {
      "authors": "/api/v1/crates/thiserror/1.0.7/authors",
      "dependencies": "/api/v1/crates/thiserror/1.0.7/dependencies",
      "version_downloads": "/api/v1/crates/thiserror/1.0.7/downloads"
    },
    "num": "1.0.7",
    "published_by": {
      "avatar": "https://avatars2.githubusercontent.com/u/1940490?v=4",
      "id": 3618, "login": "dtolnay", "name": "David Tolnay",
      "url": "https://github.com/dtolnay"
    },
    "readme_path": "/api/v1/crates/thiserror/1.0.7/readme",
    "updated_at": "2019-12-03T17:52:04.021834+00:00", "yanked": false
  },
  {
    "audit_actions": [],
    "authors": {
      "meta": {"names": ["David Tolnay <dtolnay@gmail.com>"]},
      "users": []
    },
    "crate": "thiserror", "crate_size": 12598,
    "created_at": "2019-12-03T18:23:55.700762+00:00",
    "dependencies": [
      {
        "crate_id": "anyhow", "default_features": true, "downloads": 0,
        "features": [], "id": 1021525, "kind": "dev", "optional": false,
        "req": "^1.0", "target": null, "version_id": 193733
      },
      {
        "crate_id": "ref-cast", "default_features": true, "downloads": 0,
        "features": [], "id": 1021526, "kind": "dev", "optional": false,
        "req": "^1.0", "target": null, "version_id": 193733
      },
      {
        "crate_id": "rustversion", "default_features": true, "downloads": 0,
        "features": [], "id": 1021527, "kind": "dev", "optional": false,
        "req": "^1.0", "target": null, "version_id": 193733
      },
      {
        "crate_id": "thiserror-impl", "default_features": true,
        "downloads": 0, "features": [], "id": 1021524, "kind": "normal",
        "optional": false, "req": "=1.0.8", "target": null,
        "version_id": 193733
      },
      {
        "crate_id": "trybuild", "default_features": true, "downloads": 0,
        "features": [], "id": 1021528, "kind": "dev", "optional": false,
        "req": "^1.0", "target": null, "version_id": 193733
      }
    ],
    "dl_path": "/api/v1/crates/thiserror/1.0.8/download",
    "downloads": 2104, "features": {}, "id": 193733,
    "license": "MIT OR Apache-2.0",
    "links": {
      "authors": "/api/v1/crates/thiserror/1.0.8/authors",
      "dependencies": "/api/v1/crates/thiserror/1.0.8/dependencies",
      "version_downloads": "/api/v1/crates/thiserror/1.0.8/downloads"
    },
    "num": "1.0.8",
    "published_by": {
      "avatar": "https://avatars2.githubusercontent.com/u/1940490?v=4",
      "id": 3618, "login": "dtolnay", "name": "David Tolnay",
      "url": "https://github.com/dtolnay"
    },
    "readme_path": "/api/v1/crates/thiserror/1.0.8/readme",
    "updated_at": "2019-12-03T18:23:55.700762+00:00", "yanked": false
  },
  {
    "audit_actions": [],
    "authors": {
      "meta": {"names": ["David Tolnay <dtolnay@gmail.com>"]},
      "users": []
    },
    "crate": "thiserror", "crate_size": 12450,
    "created_at": "2019-12-04T03:37:22.081961+00:00",
    "dependencies": [
      {
        "crate_id": "anyhow", "default_features": true, "downloads": 0,
        "features": [], "id": 1022214, "kind": "dev", "optional": false,
        "req": "^1.0", "target": null, "version_id": 193837
      },
      {
        "crate_id": "ref-cast", "default_features": true, "downloads": 0,
        "features": [], "id": 1022215, "kind": "dev", "optional": false,
        "req": "^1.0", "target": null, "version_id": 193837
      },
      {
        "crate_id": "rustversion", "default_features": true, "downloads": 0,
        "features": [], "id": 1022216, "kind": "dev", "optional": false,
        "req": "^1.0", "target": null, "version_id": 193837
      },
      {
        "crate_id": "thiserror-impl", "default_features": true,
        "downloads": 0, "features": [], "id": 1022213, "kind": "normal",
        "optional": false, "req": "=1.0.9", "target": null,
        "version_id": 193837
      },
      {
        "crate_id": "trybuild", "default_features": true, "downloads": 0,
        "features": [], "id": 1022217, "kind": "dev", "optional": false,
        "req": "^1.0", "target": null, "version_id": 193837
      }
    ],
    "dl_path": "/api/v1/crates/thiserror/1.0.9/download",
    "downloads": 193848, "features": {}, "id": 193837,
    "license": "MIT OR Apache-2.0",
    "links": {
      "authors": "/api/v1/crates/thiserror/1.0.9/authors",
      "dependencies": "/api/v1/crates/thiserror/1.0.9/dependencies",
      "version_downloads": "/api/v1/crates/thiserror/1.0.9/downloads"
    },
    "num": "1.0.9",
    "published_by": {
      "avatar": "https://avatars2.githubusercontent.com/u/1940490?v=4",
      "id": 3618, "login": "dtolnay", "name": "David Tolnay",
      "url": "https://github.com/dtolnay"
    },
    "readme_path": "/api/v1/crates/thiserror/1.0.9/readme",
    "updated_at": "2019-12-04T03:37:22.081961+00:00", "yanked": false
  },
  {
    "audit_actions": [
      {
        "action": "publish", "time": "2020-01-28T19:52:00.755701+00:00",
        "user": {
          "avatar": "https://avatars2.githubusercontent.com/u/1940490?v=4",
          "id": 3618, "login": "dtolnay", "name": "David Tolnay",
          "url": "https://github.com/dtolnay"
        }
      }
    ],
    "authors": {
      "meta": {"names": ["David Tolnay <dtolnay@gmail.com>"]},
      "users": []
    },
    "crate": "thiserror", "crate_size": 13091,
    "created_at": "2020-01-28T19:52:00.755701+00:00",
    "dependencies": [
      {
        "crate_id": "anyhow", "default_features": true, "downloads": 0,
        "features": [], "id": 1115842, "kind": "dev", "optional": false,
        "req": "^1.0", "target": null, "version_id": 207604
      },
      {
        "crate_id": "ref-cast", "default_features": true, "downloads": 0,
        "features": [], "id": 1115843, "kind": "dev", "optional": false,
        "req": "^1.0", "target": null, "version_id": 207604
      },
      {
        "crate_id": "rustversion", "default_features": true, "downloads": 0,
        "features": [], "id": 1115844, "kind": "dev", "optional": false,
        "req": "^1.0", "target": null, "version_id": 207604
      },
      {
        "crate_id": "thiserror-impl", "default_features": true,
        "downloads": 0, "features": [], "id": 1115841, "kind": "normal",
        "optional": false, "req": "=1.0.10", "target": null,
        "version_id": 207604
      },
      {
        "crate_id": "trybuild", "default_features": true, "downloads": 0,
        "features": ["diff"], "id": 1115845, "kind": "dev",
        "optional": false, "req": "^1.0.19", "target": null,
        "version_id": 207604
      }
    ],
    "dl_path": "/api/v1/crates/thiserror/1.0.10/download",
    "downloads": 159851, "features": {}, "id": 207604,
    "license": "MIT OR Apache-2.0",
    "links": {
      "authors": "/api/v1/crates/thiserror/1.0.10/authors",
      "dependencies": "/api/v1/crates/thiserror/1.0.10/dependencies",
      "version_downloads": "/api/v1/crates/thiserror/1.0.10/downloads"
    },
    "num": "1.0.10",
    "published_by": {
      "avatar": "https://avatars2.githubusercontent.com/u/1940490?v=4",
      "id": 3618, "login": "dtolnay", "name": "David Tolnay",
      "url": "https://github.com/dtolnay"
    },
    "readme_path": "/api/v1/crates/thiserror/1.0.10/readme",
    "updated_at": "2020-01-28T19:52:00.755701+00:00", "yanked": false
  },
  {
    "audit_actions": [
      {
        "action": "publish", "time": "2020-02-14T19:12:49.751935+00:00",
        "user": {
          "avatar": "https://avatars2.githubusercontent.com/u/1940490?v=4",
          "id": 3618, "login": "dtolnay", "name": "David Tolnay",
          "url": "https://github.com/dtolnay"
        }
      }
    ],
    "authors": {
      "meta": {"names": ["David Tolnay <dtolnay@gmail.com>"]},
      "users": []
    },
    "crate": "thiserror", "crate_size": 13114,
    "created_at": "2020-02-14T19:12:49.751935+00:00",
    "dependencies": [
      {
        "crate_id": "anyhow", "default_features": true, "downloads": 0,
        "features": [], "id": 1153656, "kind": "dev", "optional": false,
        "req": "^1.0", "target": null, "version_id": 212570
      },
      {
        "crate_id": "ref-cast", "default_features": true, "downloads": 0,
        "features": [], "id": 1153657, "kind": "dev", "optional": false,
        "req": "^1.0", "target": null, "version_id": 212570
      },
      {
        "crate_id": "rustversion", "default_features": true, "downloads": 0,
        "features": [], "id": 1153658, "kind": "dev", "optional": false,
        "req": "^1.0", "target": null, "version_id": 212570
      },
      {
        "crate_id": "thiserror-impl", "default_features": true,
        "downloads": 0, "features": [], "id": 1153655, "kind": "normal",
        "optional": false, "req": "=1.0.11", "target": null,
        "version_id": 212570
      },
      {
        "crate_id": "trybuild", "default_features": true, "downloads": 0,
        "features": ["diff"], "id": 1153659, "kind": "dev",
        "optional": false, "req": "^1.0.19", "target": null,
        "version_id": 212570
      }
    ],
    "dl_path": "/api/v1/crates/thiserror/1.0.11/download",
    "downloads": 385352, "features": {}, "id": 212570,
    "license": "MIT OR Apache-2.0",
    "links": {
      "authors": "/api/v1/crates/thiserror/1.0.11/authors",
      "dependencies": "/api/v1/crates/thiserror/1.0.11/dependencies",
      "version_downloads": "/api/v1/crates/thiserror/1.0.11/downloads"
    },
    "num": "1.0.11",
    "published_by": {
      "avatar": "https://avatars2.githubusercontent.com/u/1940490?v=4",
      "id": 3618, "login": "dtolnay", "name": "David Tolnay",
      "url": "https://github.com/dtolnay"
    },
    "readme_path": "/api/v1/crates/thiserror/1.0.11/readme",
    "updated_at": "2020-02-14T19:12:49.751935+00:00", "yanked": false
  },
  {
    "audit_actions": [
      {
        "action": "publish", "time": "2020-03-21T05:51:08.794599+00:00",
        "user": {
          "avatar": "https://avatars2.githubusercontent.com/u/1940490?v=4",
          "id": 3618, "login": "dtolnay", "name": "David Tolnay",
          "url": "https://github.com/dtolnay"
        }
      }
    ],
    "authors": {
      "meta": {"names": ["David Tolnay <dtolnay@gmail.com>"]},
      "users": []
    },
    "crate": "thiserror", "crate_size": 13929,
    "created_at": "2020-03-21T05:51:08.794599+00:00",
    "dependencies": [
      {
        "crate_id": "anyhow", "default_features": true, "downloads": 0,
        "features": [], "id": 1232068, "kind": "dev", "optional": false,
        "req": "^1.0", "target": null, "version_id": 223021
      },
      {
        "crate_id": "ref-cast", "default_features": true, "downloads": 0,
        "features": [], "id": 1232069, "kind": "dev", "optional": false,
        "req": "^1.0", "target": null, "version_id": 223021
      },
      {
        "crate_id": "rustversion", "default_features": true, "downloads": 0,
        "features": [], "id": 1232070, "kind": "dev", "optional": false,
        "req": "^1.0", "target": null, "version_id": 223021
      },
      {
        "crate_id": "thiserror-impl", "default_features": true,
        "downloads": 0, "features": [], "id": 1232067, "kind": "normal",
        "optional": false, "req": "=1.0.12", "target": null,
        "version_id": 223021
      },
      {
        "crate_id": "trybuild", "default_features": true, "downloads": 0,
        "features": ["diff"], "id": 1232071, "kind": "dev",
        "optional": false, "req": "^1.0.19", "target": null,
        "version_id": 223021
      }
    ],
    "dl_path": "/api/v1/crates/thiserror/1.0.12/download",
    "downloads": 10235, "features": {}, "id": 223021,
    "license": "MIT OR Apache-2.0",
    "links": {
      "authors": "/api/v1/crates/thiserror/1.0.12/authors",
      "dependencies": "/api/v1/crates/thiserror/1.0.12/dependencies",
      "version_downloads": "/api/v1/crates/thiserror/1.0.12/downloads"
    },
    "num": "1.0.12",
    "published_by": {
      "avatar": "https://avatars2.githubusercontent.com/u/1940490?v=4",
      "id": 3618, "login": "dtolnay", "name": "David Tolnay",
      "url": "https://github.com/dtolnay"
    },
    "readme_path": "/api/v1/crates/thiserror/1.0.12/readme",
    "updated_at": "2020-03-21T05:51:08.794599+00:00", "yanked": false
  },
  {
    "audit_actions": [
      {
        "action": "publish", "time": "2020-03-23T06:14:36.085940+00:00",
        "user": {
          "avatar": "https://avatars2.githubusercontent.com/u/1940490?v=4",
          "id": 3618, "login": "dtolnay", "name": "David Tolnay",
          "url": "https://github.com/dtolnay"
        }
      }
    ],
    "authors": {
      "meta": {"names": ["David Tolnay <dtolnay@gmail.com>"]},
      "users": []
    },
    "crate": "thiserror", "crate_size": 14155,
    "created_at": "2020-03-23T06:14:36.085940+00:00",
    "dependencies": [
      {
        "crate_id": "anyhow", "default_features": true, "downloads": 0,
        "features": [], "id": 1235489, "kind": "dev", "optional": false,
        "req": "^1.0", "target": null, "version_id": 223603
      },
      {
        "crate_id": "ref-cast", "default_features": true, "downloads": 0,
        "features": [], "id": 1235490, "kind": "dev", "optional": false,
        "req": "^1.0", "target": null, "version_id": 223603
      },
      {
        "crate_id": "rustversion", "default_features": true, "downloads": 0,
        "features": [], "id": 1235491, "kind": "dev", "optional": false,
        "req": "^1.0", "target": null, "version_id": 223603
      },
      {
        "crate_id": "thiserror-impl", "default_features": true,
        "downloads": 0, "features": [], "id": 1235488, "kind": "normal",
        "optional": false, "req": "=1.0.13", "target": null,
        "version_id": 223603
      },
      {
        "crate_id": "trybuild", "default_features": true, "downloads": 0,
        "features": ["diff"], "id": 1235492, "kind": "dev",
        "optional": false, "req": "^1.0.19", "target": null,
        "version_id": 223603
      }
    ],
    "dl_path": "/api/v1/crates/thiserror/1.0.13/download",
    "downloads": 74111, "features": {}, "id": 223603,
    "license": "MIT OR Apache-2.0",
    "links": {
      "authors": "/api/v1/crates/thiserror/1.0.13/authors",
      "dependencies": "/api/v1/crates/thiserror/1.0.13/dependencies",
      "version_downloads": "/api/v1/crates/thiserror/1.0.13/downloads"
    },
    "num": "1.0.13",
    "published_by": {
      "avatar": "https://avatars2.githubusercontent.com/u/1940490?v=4",
      "id": 3618, "login": "dtolnay", "name": "David Tolnay",
      "url": "https://github.com/dtolnay"
    },
    "readme_path": "/api/v1/crates/thiserror/1.0.13/readme",
    "updated_at": "2020-03-23T06:14:36.085940+00:00", "yanked": false
  },
  {
    "audit_actions": [
      {
        "action": "publish", "time": "2020-03-29T15:47:47.178031+00:00",
        "user": {
          "avatar": "https://avatars2.githubusercontent.com/u/1940490?v=4",
          "id": 3618, "login": "dtolnay", "name": "David Tolnay",
          "url": "https://github.com/dtolnay"
        }
      }
    ],
    "authors": {
      "meta": {"names": ["David Tolnay <dtolnay@gmail.com>"]},
      "users": []
    },
    "crate": "thiserror", "crate_size": 14224,
    "created_at": "2020-03-29T15:47:47.178031+00:00",
    "dependencies": [
      {
        "crate_id": "anyhow", "default_features": true, "downloads": 0,
        "features": [], "id": 1252382, "kind": "dev", "optional": false,
        "req": "^1.0", "target": null, "version_id": 225762
      },
      {
        "crate_id": "ref-cast", "default_features": true, "downloads": 0,
        "features": [], "id": 1252383, "kind": "dev", "optional": false,
        "req": "^1.0", "target": null, "version_id": 225762
      },
      {
        "crate_id": "rustversion", "default_features": true, "downloads": 0,
        "features": [], "id": 1252384, "kind": "dev", "optional": false,
        "req": "^1.0", "target": null, "version_id": 225762
      },
      {
        "crate_id": "thiserror-impl", "default_features": true,
        "downloads": 0, "features": [], "id": 1252381, "kind": "normal",
        "optional": false, "req": "=1.0.14", "target": null,
        "version_id": 225762
      },
      {
        "crate_id": "trybuild", "default_features": true, "downloads": 0,
        "features": ["diff"], "id": 1252385, "kind": "dev",
        "optional": false, "req": "^1.0.19", "target": null,
        "version_id": 225762
      }
    ],
    "dl_path": "/api/v1/crates/thiserror/1.0.14/download",
    "downloads": 168886, "features": {}, "id": 225762,
    "license": "MIT OR Apache-2.0",
    "links": {
      "authors": "/api/v1/crates/thiserror/1.0.14/authors",
      "dependencies": "/api/v1/crates/thiserror/1.0.14/dependencies",
      "version_downloads": "/api/v1/crates/thiserror/1.0.14/downloads"
    },
    "num": "1.0.14",
    "published_by": {
      "avatar": "https://avatars2.githubusercontent.com/u/1940490?v=4",
      "id": 3618, "login": "dtolnay", "name": "David Tolnay",
      "url": "https://github.com/dtolnay"
    },
    "readme_path": "/api/v1/crates/thiserror/1.0.14/readme",
    "updated_at": "2020-03-29T15:47:47.178031+00:00", "yanked": false
  },
  {
    "audit_actions": [
      {
        "action": "publish", "time": "2020-04-11T18:38:23.209136+00:00",
        "user": {
          "avatar": "https://avatars2.githubusercontent.com/u/1940490?v=4",
          "id": 3618, "login": "dtolnay", "name": "David Tolnay",
          "url": "https://github.com/dtolnay"
        }
      }
    ],
    "authors": {
      "meta": {"names": ["David Tolnay <dtolnay@gmail.com>"]},
      "users": []
    },
    "crate": "thiserror", "crate_size": 14448,
    "created_at": "2020-04-11T18:38:23.209136+00:00",
    "dependencies": [
      {
        "crate_id": "anyhow", "default_features": true, "downloads": 0,
        "features": [], "id": 1283508, "kind": "dev", "optional": false,
        "req": "^1.0", "target": null, "version_id": 229971
      },
      {
        "crate_id": "ref-cast", "default_features": true, "downloads": 0,
        "features": [], "id": 1283509, "kind": "dev", "optional": false,
        "req": "^1.0", "target": null, "version_id": 229971
      },
      {
        "crate_id": "rustversion", "default_features": true, "downloads": 0,
        "features": [], "id": 1283510, "kind": "dev", "optional": false,
        "req": "^1.0", "target": null, "version_id": 229971
      },
      {
        "crate_id": "thiserror-impl", "default_features": true,
        "downloads": 0, "features": [], "id": 1283507, "kind": "normal",
        "optional": false, "req": "=1.0.15", "target": null,
        "version_id": 229971
      },
      {
        "crate_id": "trybuild", "default_features": true, "downloads": 0,
        "features": ["diff"], "id": 1283511, "kind": "dev",
        "optional": false, "req": "^1.0.19", "target": null,
        "version_id": 229971
      }
    ],
    "dl_path": "/api/v1/crates/thiserror/1.0.15/download",
    "downloads": 268718, "features": {}, "id": 229971,
    "license": "MIT OR Apache-2.0",
    "links": {
      "authors": "/api/v1/crates/thiserror/1.0.15/authors",
      "dependencies": "/api/v1/crates/thiserror/1.0.15/dependencies",
      "version_downloads": "/api/v1/crates/thiserror/1.0.15/downloads"
    },
    "num": "1.0.15",
    "published_by": {
      "avatar": "https://avatars2.githubusercontent.com/u/1940490?v=4",
      "id": 3618, "login": "dtolnay", "name": "David Tolnay",
      "url": "https://github.com/dtolnay"
    },
    "readme_path": "/api/v1/crates/thiserror/1.0.15/readme",
    "updated_at": "2020-04-11T18:38:23.209136+00:00", "yanked": false
  },
  {
    "audit_actions": [
      {
        "action": "publish", "time": "2020-04-27T22:53:58.737540+00:00",
        "user": {
          "avatar": "https://avatars2.githubusercontent.com/u/1940490?v=4",
          "id": 3618, "login": "dtolnay", "name": "David Tolnay",
          "url": "https://github.com/dtolnay"
        }
      }
    ],
    "authors": {
      "meta": {"names": ["David Tolnay <dtolnay@gmail.com>"]},
      "users": []
    },
    "crate": "thiserror", "crate_size": 14688,
    "created_at": "2020-04-27T22:53:58.737540+00:00",
    "dependencies": [
      {
        "crate_id": "anyhow", "default_features": true, "downloads": 0,
        "features": [], "id": 1324181, "kind": "dev", "optional": false,
        "req": "^1.0", "target": null, "version_id": 235409
      },
      {
        "crate_id": "ref-cast", "default_features": true, "downloads": 0,
        "features": [], "id": 1324182, "kind": "dev", "optional": false,
        "req": "^1.0", "target": null, "version_id": 235409
      },
      {
        "crate_id": "rustversion", "default_features": true, "downloads": 0,
        "features": [], "id": 1324183, "kind": "dev", "optional": false,
        "req": "^1.0", "target": null, "version_id": 235409
      },
      {
        "crate_id": "thiserror-impl", "default_features": true,
        "downloads": 0, "features": [], "id": 1324180, "kind": "normal",
        "optional": false, "req": "=1.0.16", "target": null,
        "version_id": 235409
      },
      {
        "crate_id": "trybuild", "default_features": true, "downloads": 0,
        "features": ["diff"], "id": 1324184, "kind": "dev",
        "optional": false, "req": "^1.0.19", "target": null,
        "version_id": 235409
      }
    ],
    "dl_path": "/api/v1/crates/thiserror/1.0.16/download",
    "downloads": 299099, "features": {}, "id": 235409,
    "license": "MIT OR Apache-2.0",
    "links": {
      "authors": "/api/v1/crates/thiserror/1.0.16/authors",
      "dependencies": "/api/v1/crates/thiserror/1.0.16/dependencies",
      "version_downloads": "/api/v1/crates/thiserror/1.0.16/downloads"
    },
    "num": "1.0.16",
    "published_by": {
      "avatar": "https://avatars2.githubusercontent.com/u/1940490?v=4",
      "id": 3618, "login": "dtolnay", "name": "David Tolnay",
      "url": "https://github.com/dtolnay"
    },
    "readme_path": "/api/v1/crates/thiserror/1.0.16/readme",
    "updated_at": "2020-04-27T22:53:58.737540+00:00", "yanked": false
  },
  {
    "audit_actions": [
      {
        "action": "publish", "time": "2020-05-13T05:47:45.066697+00:00",
        "user": {
          "avatar": "https://avatars2.githubusercontent.com/u/1940490?v=4",
          "id": 3618, "login": "dtolnay", "name": "David Tolnay",
          "url": "https://github.com/dtolnay"
        }
      }
    ],
    "authors": {
      "meta": {"names": ["David Tolnay <dtolnay@gmail.com>"]},
      "users": []
    },
    "crate": "thiserror", "crate_size": 15651,
    "created_at": "2020-05-13T05:47:45.066697+00:00",
    "dependencies": [
      {
        "crate_id": "anyhow", "default_features": true, "downloads": 0,
        "features": [], "id": 1362935, "kind": "dev", "optional": false,
        "req": "^1.0", "target": null, "version_id": 240876
      },
      {
        "crate_id": "ref-cast", "default_features": true, "downloads": 0,
        "features": [], "id": 1362936, "kind": "dev", "optional": false,
        "req": "^1.0", "target": null, "version_id": 240876
      },
      {
        "crate_id": "rustversion", "default_features": true, "downloads": 0,
        "features": [], "id": 1362937, "kind": "dev", "optional": false,
        "req": "^1.0", "target": null, "version_id": 240876
      },
      {
        "crate_id": "thiserror-impl", "default_features": true,
        "downloads": 0, "features": [], "id": 1362934, "kind": "normal",
        "optional": false, "req": "=1.0.17", "target": null,
        "version_id": 240876
      },
      {
        "crate_id": "trybuild", "default_features": true, "downloads": 0,
        "features": ["diff"], "id": 1362938, "kind": "dev",
        "optional": false, "req": "^1.0.19", "target": null,
        "version_id": 240876
      }
    ],
    "dl_path": "/api/v1/crates/thiserror/1.0.17/download",
    "downloads": 46802, "features": {}, "id": 240876,
    "license": "MIT OR Apache-2.0",
    "links": {
      "authors": "/api/v1/crates/thiserror/1.0.17/authors",
      "dependencies": "/api/v1/crates/thiserror/1.0.17/dependencies",
      "version_downloads": "/api/v1/crates/thiserror/1.0.17/downloads"
    },
    "num": "1.0.17",
    "published_by": {
      "avatar": "https://avatars2.githubusercontent.com/u/1940490?v=4",
      "id": 3618, "login": "dtolnay", "name": "David Tolnay",
      "url": "https://github.com/dtolnay"
    },
    "readme_path": "/api/v1/crates/thiserror/1.0.17/readme",
    "updated_at": "2020-05-13T05:47:45.066697+00:00", "yanked": false
  },
  {
    "audit_actions": [
      {
        "action": "publish", "time": "2020-05-15T23:51:12.190279+00:00",
        "user": {
          "avatar": "https://avatars2.githubusercontent.com/u/1940490?v=4",
          "id": 3618, "login": "dtolnay", "name": "David Tolnay",
          "url": "https://github.com/dtolnay"
        }
      }
    ],
    "authors": {
      "meta": {"names": ["David Tolnay <dtolnay@gmail.com>"]},
      "users": []
    },
    "crate": "thiserror", "crate_size": 15786,
    "created_at": "2020-05-15T23:51:12.190279+00:00",
    "dependencies": [
      {
        "crate_id": "anyhow", "default_features": true, "downloads": 0,
        "features": [], "id": 1371233, "kind": "dev", "optional": false,
        "req": "^1.0", "target": null, "version_id": 241980
      },
      {
        "crate_id": "ref-cast", "default_features": true, "downloads": 0,
        "features": [], "id": 1371234, "kind": "dev", "optional": false,
        "req": "^1.0", "target": null, "version_id": 241980
      },
      {
        "crate_id": "rustversion", "default_features": true, "downloads": 0,
        "features": [], "id": 1371235, "kind": "dev", "optional": false,
        "req": "^1.0", "target": null, "version_id": 241980
      },
      {
        "crate_id": "thiserror-impl", "default_features": true,
        "downloads": 0, "features": [], "id": 1371232, "kind": "normal",
        "optional": false, "req": "=1.0.18", "target": null,
        "version_id": 241980
      },
      {
        "crate_id": "trybuild", "default_features": true, "downloads": 0,
        "features": ["diff"], "id": 1371236, "kind": "dev",
        "optional": false, "req": "^1.0.19", "target": null,
        "version_id": 241980
      }
    ],
    "dl_path": "/api/v1/crates/thiserror/1.0.18/download",
    "downloads": 109845, "features": {}, "id": 241980,
    "license": "MIT OR Apache-2.0",
    "links": {
      "authors": "/api/v1/crates/thiserror/1.0.18/authors",
      "dependencies": "/api/v1/crates/thiserror/1.0.18/dependencies",
      "version_downloads": "/api/v1/crates/thiserror/1.0.18/downloads"
    },
    "num": "1.0.18",
    "published_by": {
      "avatar": "https://avatars2.githubusercontent.com/u/1940490?v=4",
      "id": 3618, "login": "dtolnay", "name": "David Tolnay",
      "url": "https://github.com/dtolnay"
    },
    "readme_path": "/api/v1/crates/thiserror/1.0.18/readme",
    "updated_at": "2020-05-15T23:51:12.190279+00:00", "yanked": false
  },
  {
    "audit_actions": [
      {
        "action": "publish", "time": "2020-05-22T02:06:44.867272+00:00",
        "user": {
          "avatar": "https://avatars2.githubusercontent.com/u/1940490?v=4",
          "id": 3618, "login": "dtolnay", "name": "David Tolnay",
          "url": "https://github.com/dtolnay"
        }
      }
    ],
    "authors": {
      "meta": {"names": ["David Tolnay <dtolnay@gmail.com>"]},
      "users": []
    },
    "crate": "thiserror", "crate_size": 15777,
    "created_at": "2020-05-22T02:06:44.867272+00:00",
    "dependencies": [
      {
        "crate_id": "anyhow", "default_features": true, "downloads": 0,
        "features": [], "id": 1385523, "kind": "dev", "optional": false,
        "req": "^1.0", "target": null, "version_id": 243969
      },
      {
        "crate_id": "ref-cast", "default_features": true, "downloads": 0,
        "features": [], "id": 1385524, "kind": "dev", "optional": false,
        "req": "^1.0", "target": null, "version_id": 243969
      },
      {
        "crate_id": "rustversion", "default_features": true, "downloads": 0,
        "features": [], "id": 1385525, "kind": "dev", "optional": false,
        "req": "^1.0", "target": null, "version_id": 243969
      },
      {
        "crate_id": "thiserror-impl", "default_features": true,
        "downloads": 0, "features": [], "id": 1385522, "kind": "normal",
        "optional": false, "req": "=1.0.19", "target": null,
        "version_id": 243969
      },
      {
        "crate_id": "trybuild", "default_features": true, "downloads": 0,
        "features": ["diff"], "id": 1385526, "kind": "dev",
        "optional": false, "req": "^1.0.19", "target": null,
        "version_id": 243969
      }
    ],
    "dl_path": "/api/v1/crates/thiserror/1.0.19/download",
    "downloads": 465024, "features": {}, "id": 243969,
    "license": "MIT OR Apache-2.0",
    "links": {
      "authors": "/api/v1/crates/thiserror/1.0.19/authors",
      "dependencies": "/api/v1/crates/thiserror/1.0.19/dependencies",
      "version_downloads": "/api/v1/crates/thiserror/1.0.19/downloads"
    },
    "num": "1.0.19",
    "published_by": {
      "avatar": "https://avatars2.githubusercontent.com/u/1940490?v=4",
      "id": 3618, "login": "dtolnay", "name": "David Tolnay",
      "url": "https://github.com/dtolnay"
    },
    "readme_path": "/api/v1/crates/thiserror/1.0.19/readme",
    "updated_at": "2020-05-22T02:06:44.867272+00:00", "yanked": false
  },
  {
    "audit_actions": [
      {
        "action": "publish", "time": "2020-06-15T23:22:46.550357+00:00",
        "user": {
          "avatar": "https://avatars2.githubusercontent.com/u/1940490?v=4",
          "id": 3618, "login": "dtolnay", "name": "David Tolnay",
          "url": "https://github.com/dtolnay"
        }
      }
    ],
    "authors": {
      "meta": {"names": ["David Tolnay <dtolnay@gmail.com>"]},
      "users": []
    },
    "crate": "thiserror", "crate_size": 15950,
    "created_at": "2020-06-15T23:22:46.550357+00:00",
    "dependencies": [
      {
        "crate_id": "anyhow", "default_features": true, "downloads": 0,
        "features": [], "id": 1449773, "kind": "dev", "optional": false,
        "req": "^1.0", "target": null, "version_id": 252730
      },
      {
        "crate_id": "ref-cast", "default_features": true, "downloads": 0,
        "features": [], "id": 1449774, "kind": "dev", "optional": false,
        "req": "^1.0", "target": null, "version_id": 252730
      },
      {
        "crate_id": "rustversion", "default_features": true, "downloads": 0,
        "features": [], "id": 1449775, "kind": "dev", "optional": false,
        "req": "^1.0", "target": null, "version_id": 252730
      },
      {
        "crate_id": "thiserror-impl", "default_features": true,
        "downloads": 0, "features": [], "id": 1449772, "kind": "normal",
        "optional": false, "req": "=1.0.20", "target": null,
        "version_id": 252730
      },
      {
        "crate_id": "trybuild", "default_features": true, "downloads": 0,
        "features": ["diff"], "id": 1449776, "kind": "dev",
        "optional": false, "req": "^1.0.19", "target": null,
        "version_id": 252730
      }
    ],
    "dl_path": "/api/v1/crates/thiserror/1.0.20/download",
    "downloads": 2021442, "features": {}, "id": 252730,
    "license": "MIT OR Apache-2.0",
    "links": {
      "authors": "/api/v1/crates/thiserror/1.0.20/authors",
      "dependencies": "/api/v1/crates/thiserror/1.0.20/dependencies",
      "version_downloads": "/api/v1/crates/thiserror/1.0.20/downloads"
    },
    "num": "1.0.20",
    "published_by": {
      "avatar": "https://avatars2.githubusercontent.com/u/1940490?v=4",
      "id": 3618, "login": "dtolnay", "name": "David Tolnay",
      "url": "https://github.com/dtolnay"
    },
    "readme_path": "/api/v1/crates/thiserror/1.0.20/readme",
    "updated_at": "2020-06-15T23:22:46.550357+00:00", "yanked": false
  },
  {
    "audit_actions": [
      {
        "action": "publish", "time": "2020-10-06T23:56:25.569336+00:00",
        "user": {
          "avatar": "https://avatars2.githubusercontent.com/u/1940490?v=4",
          "id": 3618, "login": "dtolnay", "name": "David Tolnay",
          "url": "https://github.com/dtolnay"
        }
      }
    ],
    "authors": {
      "meta": {"names": ["David Tolnay <dtolnay@gmail.com>"]},
      "users": []
    },
    "crate": "thiserror", "crate_size": 16187,
    "created_at": "2020-10-06T23:56:25.569336+00:00",
    "dependencies": [
      {
        "crate_id": "anyhow", "default_features": true, "downloads": 0,
        "features": [], "id": 1740642, "kind": "dev", "optional": false,
        "req": "^1.0", "target": null, "version_id": 290926
      },
      {
        "crate_id": "ref-cast", "default_features": true, "downloads": 0,
        "features": [], "id": 1740643, "kind": "dev", "optional": false,
        "req": "^1.0", "target": null, "version_id": 290926
      },
      {
        "crate_id": "rustversion", "default_features": true, "downloads": 0,
        "features": [], "id": 1740644, "kind": "dev", "optional": false,
        "req": "^1.0", "target": null, "version_id": 290926
      },
      {
        "crate_id": "thiserror-impl", "default_features": true,
        "downloads": 0, "features": [], "id": 1740641, "kind": "normal",
        "optional": false, "req": "=1.0.21", "target": null,
        "version_id": 290926
      },
      {
        "crate_id": "trybuild", "default_features": true, "downloads": 0,
        "features": ["diff"], "id": 1740645, "kind": "dev",
        "optional": false, "req": "^1.0.19", "target": null,
        "version_id": 290926
      }
    ],
    "dl_path": "/api/v1/crates/thiserror/1.0.21/download",
    "downloads": 434515, "features": {}, "id": 290926,
    "license": "MIT OR Apache-2.0",
    "links": {
      "authors": "/api/v1/crates/thiserror/1.0.21/authors",
      "dependencies": "/api/v1/crates/thiserror/1.0.21/dependencies",
      "version_downloads": "/api/v1/crates/thiserror/1.0.21/downloads"
    },
    "num": "1.0.21",
    "published_by": {
      "avatar": "https://avatars2.githubusercontent.com/u/1940490?v=4",
      "id": 3618, "login": "dtolnay", "name": "David Tolnay",
      "url": "https://github.com/dtolnay"
    },
    "readme_path": "/api/v1/crates/thiserror/1.0.21/readme",
    "updated_at": "2020-10-06T23:56:25.569336+00:00", "yanked": false
  }
]